agine/__init__.py
agine/config.py
agine/api/OSOptions.py
agine/api/__init__.py
agine/commons/DistanceFunctions.py
agine/commons/GeographicalFunctions.py
agine/commons/__init__.py
agine/core/__init__.py
agine/core/point_function.py
agine/exceptions/__init__.py
agine/exceptions/_error.py
agine/exceptions/_warns.py
agine/libs/__init__.py
agine/libs/optimizationFunctions.py
agine-0.0.2.dist-info/LICENSE
agine-0.0.2.dist-info/METADATA
agine-0.0.2.dist-info/WHEEL
agine-0.0.2.dist-info/top_level.txt
agine-0.0.2.dist-info/RECORD
