Metadata-Version: 2.1
Name: agine
Version: 0.0.2
Summary: Functionalities for Points in n-Dimensional Space
Home-page: https://github.com/ZenithClown/agine
Author: Debmalya Pramanik
Author-email: 
License: UNKNOWN
Platform: UNKNOWN
Classifier: Programming Language :: Python :: 3
Classifier: License :: OSI Approved :: Apache Software License
Requires-Python: >=3.6
Requires-Dist: numpy
